quicked/__init__.py
quicked/quicked.pyi
quicked/backend/_quicked_simd.cpython-38-darwin.so
quicked/backend/_quicked_scalar.cpython-38-darwin.so
quicked-1.2.dist-info/RECORD
quicked-1.2.dist-info/WHEEL
quicked-1.2.dist-info/METADATA
quicked-1.2.dist-info/licenses/LICENSE
