Metadata-Version: 2.4
Name: QuickEd
Version: 1.2
Summary: Python bindings for QuickEd
Keywords: edit,distance,levenshtein,align,sequence,bioinformatics
Author-Email: Max Doblas <max.doblas@bsc.es>, Oscar Lostes-Cazorla <oscar.lostes@bsc.es>, Cristian Iniguez <cristian.iniguez@bsc.es>, Santiago Marco-Sola <santiagomsola@gmail.com>
Maintainer-Email: Oscar Lostes-Cazorla <oscar.lostes@bsc.es>
License-Expression: MIT
License-File: LICENSE
Classifier: Development Status :: 5 - Production/Stable
Classifier: Intended Audience :: Developers
Classifier: Intended Audience :: Science/Research
Classifier: Programming Language :: Python :: 3
Classifier: Topic :: Scientific/Engineering :: Bio-Informatics
Project-URL: Homepage, https://github.com/maxdoblas/QuickEd
Requires-Python: >=3.8
Requires-Dist: py-cpuinfo>=9.0.0
